datalayer_plane/__init__.py
datalayer_plane/__main__.py
datalayer_plane/application.py
datalayer_plane/apps/__init__.py
datalayer_plane/apps/_base.py
datalayer_plane/apps/kubernetes.py
datalayer_plane/apps/run.py
datalayer_plane/sbin/about.sh
datalayer_plane/sbin/cli.sh
datalayer_plane/sbin/delete-service-pods.sh
datalayer_plane/sbin/docker-build.sh
datalayer_plane/sbin/docker-install.sh
datalayer_plane/sbin/docker-prune.sh
datalayer_plane/sbin/docker-pull.sh
datalayer_plane/sbin/docker-push-local.sh
datalayer_plane/sbin/docker-push.sh
datalayer_plane/sbin/docker.sh
datalayer_plane/sbin/down.sh
datalayer_plane/sbin/header.sh
datalayer_plane/sbin/helm-push.sh
datalayer_plane/sbin/info.sh
datalayer_plane/sbin/jupyter-server.sh
datalayer_plane/sbin/k8s-create-namespaces.sh
datalayer_plane/sbin/k8s-prepull-cpu.sh
datalayer_plane/sbin/k8s-prepull-gpu-cuda.sh
datalayer_plane/sbin/local.sh
datalayer_plane/sbin/logs.sh
datalayer_plane/sbin/ls.sh
datalayer_plane/sbin/os.sh
datalayer_plane/sbin/pf-ceph.sh
datalayer_plane/sbin/pf-kafka.sh
datalayer_plane/sbin/pf-openfga.sh
datalayer_plane/sbin/pf-prometheus.sh
datalayer_plane/sbin/pf-pulsar.sh
datalayer_plane/sbin/pf-solr.sh
datalayer_plane/sbin/pf-traefik.sh
datalayer_plane/sbin/pf-vault.sh
datalayer_plane/sbin/ping.sh
datalayer_plane/sbin/plane.sh
datalayer_plane/sbin/reg-creds-create.sh
datalayer_plane/sbin/reup-all.sh
datalayer_plane/sbin/reup.sh
datalayer_plane/sbin/solr-help.sh
datalayer_plane/sbin/solr-init.sh
datalayer_plane/sbin/telepresence-connect.sh
datalayer_plane/sbin/telepresence-install.sh
datalayer_plane/sbin/telepresence-list.sh
datalayer_plane/sbin/telepresence-setup.sh
datalayer_plane/sbin/telepresence.sh
datalayer_plane/sbin/up.sh
datalayer_plane/sbin/use.sh
datalayer_plane/util/utils.py
datalayer_plane-0.0.5.dist-info/METADATA
datalayer_plane-0.0.5.dist-info/WHEEL
datalayer_plane-0.0.5.dist-info/entry_points.txt
datalayer_plane-0.0.5.dist-info/licenses/LICENSE
datalayer_plane-0.0.5.dist-info/RECORD
