Metadata-Version: 2.1
Name: datalayer_plane
Version: 0.0.5
License: Datalayer License
License-File: LICENSE
Classifier: Intended Audience :: Developers
Classifier: Intended Audience :: Science/Research
Classifier: Intended Audience :: System Administrators
Classifier: Programming Language :: Python
Classifier: Programming Language :: Python :: 3
Classifier: Programming Language :: Python :: 3.9
Classifier: Programming Language :: Python :: 3.10
Classifier: Programming Language :: Python :: 3.11
Requires-Python: >=3.9
Requires-Dist: avionix
Requires-Dist: boto3
Requires-Dist: clouder
Requires-Dist: datalayer-core
Requires-Dist: docker
Requires-Dist: jupyter-server<3,>=2
Requires-Dist: kopf
Requires-Dist: kubernetes
Requires-Dist: ovh
Requires-Dist: pykube-ng
Requires-Dist: rich
Requires-Dist: sshkey-tools
Requires-Dist: tabulate
Provides-Extra: test
Requires-Dist: coverage; extra == 'test'
Requires-Dist: pytest; extra == 'test'
Requires-Dist: pytest-asyncio; extra == 'test'
Requires-Dist: pytest-cov; extra == 'test'
Requires-Dist: pytest-jupyter; extra == 'test'
Requires-Dist: pytest-tornasync; extra == 'test'
